starhelm/__init__.py
starhelm/action_chunk_broker.py
starhelm/base_policy.py
starhelm/image_tools.py
starhelm/image_tools_test.py
starhelm/msgpack_numpy.py
starhelm/msgpack_numpy_test.py
starhelm/websocket_client_policy.py
starhelm/runtime/agent.py
starhelm/runtime/environment.py
starhelm/runtime/runtime.py
starhelm/runtime/subscriber.py
starhelm/runtime/agents/policy_agent.py
starhelm-0.1.2.dist-info/METADATA
starhelm-0.1.2.dist-info/WHEEL
starhelm-0.1.2.dist-info/RECORD
