Metadata-Version: 2.4
Name: starhelm
Version: 0.1.2
Requires-Python: >=3.7
Requires-Dist: dm-tree>=0.1.8
Requires-Dist: msgpack>=1.0.5
Requires-Dist: pillow>=9.0.0
Requires-Dist: tree>=0.2.4
Requires-Dist: websockets>=11.0
